pytest_html_report/CONTRIBUTING.md
pytest_html_report/__init__.py
pytest_html_report/config.py
pytest_html_report/default_config.yml
pytest_html_report/plugin.py
pytest_html_report/report_generator.py
pytest_html_report/templates/report_template.html
pytest_html_report-1.0.6.dist-info/licenses/LICENSE
pytest_html_report-1.0.6.dist-info/METADATA
pytest_html_report-1.0.6.dist-info/WHEEL
pytest_html_report-1.0.6.dist-info/entry_points.txt
pytest_html_report-1.0.6.dist-info/top_level.txt
pytest_html_report-1.0.6.dist-info/RECORD
