Metadata-Version: 2.4
Name: pytest-html-report
Version: 1.0.6
Summary: Enhanced HTML reporting for pytest with categories, specifications, and detailed logging
Home-page: https://gitlab.com/fabdullah230/pytest-html-report
Author: Fardin Chowdhury
Author-email: Fardin Chowdhury <fabdullah230@gmail.com>
Maintainer-email: Fardin Chowdhury <fabdullah230@gmail.com>
License: MIT
Project-URL: Homepage, https://gitlab.com/fabdullah230/pytest-html-report
Project-URL: Repository, https://gitlab.com/fabdullah230/pytest-html-report
Project-URL: Issues, https://gitlab.com/fabdullah230/pytest-html-report/-/issues
Project-URL: Documentation, https://gitlab.com/fabdullah230/pytest-html-report/-/blob/main/README.md
Keywords: pytest,testing,html,report,test-report
Classifier: Development Status :: 4 - Beta
Classifier: Framework :: Pytest
Classifier: Intended Audience :: Developers
Classifier: License :: OSI Approved :: MIT License
Classifier: Operating System :: OS Independent
Classifier: Programming Language :: Python
Classifier: Programming Language :: Python :: 3
Classifier: Programming Language :: Python :: 3.7
Classifier: Programming Language :: Python :: 3.8
Classifier: Programming Language :: Python :: 3.9
Classifier: Programming Language :: Python :: 3.10
Classifier: Programming Language :: Python :: 3.11
Classifier: Topic :: Software Development :: Testing
Requires-Python: >=3.7
License-File: LICENSE
Requires-Dist: pytest>=6.0
Requires-Dist: pyyaml>=5.3
Requires-Dist: beautifulsoup4>=4.9
Dynamic: author
Dynamic: home-page
Dynamic: license-file
Dynamic: requires-python
